COPYING
MANIFEST.in
README.md
requirements.txt
setup.py
ejson/__init__.py
ejson/serializers.py
ejson.egg-info/PKG-INFO
ejson.egg-info/SOURCES.txt
ejson.egg-info/dependency_links.txt
ejson.egg-info/requires.txt
ejson.egg-info/top_level.txt