Metadata-Version: 1.1
Name: ejson
Version: 0.1.3
Summary: Extensible json serializer/deserializer library
Home-page: https://github.com/Yipit/ejson
Author: Lincoln de Sousa
Author-email: lincoln@comum.org
License: GPL
Platform: UNKNOWN
Classifier: Development Status :: 4 - Beta
Classifier: Intended Audience :: Developers
Classifier: License :: OSI Approved :: GNU General Public License v3 or later (GPLv3+)
Classifier: Natural Language :: English
Classifier: Operating System :: Microsoft
Classifier: Operating System :: POSIX
Classifier: Programming Language :: Python
Classifier: Programming Language :: Python :: 2.7
